ghedesigner/__init__.py
ghedesigner/building.py
ghedesigner/constants.py
ghedesigner/enums.py
ghedesigner/ghe/__init__.py
ghedesigner/ghe/boreholes/__init__.py
ghedesigner/ghe/boreholes/base.py
ghedesigner/ghe/boreholes/coaxial_borehole.py
ghedesigner/ghe/boreholes/core.py
ghedesigner/ghe/boreholes/factory.py
ghedesigner/ghe/boreholes/multi_u_borehole.py
ghedesigner/ghe/boreholes/single_u_borehole.py
ghedesigner/ghe/coordinates.py
ghedesigner/ghe/design/__init__.py
ghedesigner/ghe/design/base.py
ghedesigner/ghe/design/birectangle.py
ghedesigner/ghe/design/birectangle_constrained.py
ghedesigner/ghe/design/bizoned.py
ghedesigner/ghe/design/near_square.py
ghedesigner/ghe/design/rectangle.py
ghedesigner/ghe/design/rowwise.py
ghedesigner/ghe/domains.py
ghedesigner/ghe/gfunction.py
ghedesigner/ghe/ground_heat_exchangers.py
ghedesigner/ghe/ground_loads.py
ghedesigner/ghe/manager.py
ghedesigner/ghe/pipe.py
ghedesigner/ghe/rowwise.py
ghedesigner/ghe/search/__init__.py
ghedesigner/ghe/search/bisection_1d.py
ghedesigner/ghe/search/bisection_2d.py
ghedesigner/ghe/search/bisection_zd.py
ghedesigner/ghe/search/rowwise.py
ghedesigner/ghe/shape.py
ghedesigner/heat_pump.py
ghedesigner/main.py
ghedesigner/media.py
ghedesigner/output/__init__.py
ghedesigner/output/converters.py
ghedesigner/output/formatters.py
ghedesigner/output/json_serializer.py
ghedesigner/output/manager.py
ghedesigner/output/text_serializer.py
ghedesigner/schemas/ghedesigner.schema.json
ghedesigner/system.py
ghedesigner/utilities.py
ghedesigner/validate.py
ghedesigner-2.1.0.dist-info/licenses/LICENSE
ghedesigner-2.1.0.dist-info/WHEEL
ghedesigner-2.1.0.dist-info/entry_points.txt
ghedesigner-2.1.0.dist-info/METADATA
ghedesigner-2.1.0.dist-info/RECORD
