Metadata-Version: 2.4
Name: ghedesigner
Version: 2.1.0
Summary: A ground heat exchanger design tool with the capability to select and size flexibly configured borehole fields that are customized for specific building and property constraints.
Author: Jeffrey D. Spitler
Author-email: Jeffrey D. Spitler <spitler@okstate.edu>
License-Expression: BSD-3-Clause
License-File: LICENSE
Classifier: Development Status :: 5 - Production/Stable
Classifier: Intended Audience :: Science/Research
Classifier: Operating System :: OS Independent
Classifier: Programming Language :: Python :: 3
Classifier: Programming Language :: Python :: 3 :: Only
Classifier: Programming Language :: Python :: 3.10
Classifier: Programming Language :: Python :: 3.11
Classifier: Programming Language :: Python :: 3.12
Classifier: Programming Language :: Python :: 3.13
Classifier: Programming Language :: Python :: 3.14
Classifier: Topic :: Scientific/Engineering
Requires-Dist: bhresist>=0.3
Requires-Dist: click>=8.3.1
Requires-Dist: jsonschema>=4.26.0
Requires-Dist: numpy>=2.2.6
Requires-Dist: pygfunction>=2.3.1
Requires-Dist: scipy>=1.15.3
Requires-Dist: secondarycoolantprops>=1.4
Requires-Python: >=3.10
